ntfy_sdk_python/__init__.py
ntfy_sdk_python/ntfy.py
ntfy_sdk_python-0.0.1.dist-info/WHEEL
ntfy_sdk_python-0.0.1.dist-info/METADATA
ntfy_sdk_python-0.0.1.dist-info/RECORD
